somador_sub/bcd7seg.vhd
-- by @jtfrl

-- DISPLAY DE SETE SEGMENTOS
-- ENTRADA
-- dados de soma ou subtração
-- SAÍDA
-- resultado da soma
-- idem para sub. (deve mostrar '-' se o res. é negativo)

library IEEE;
use IEEE.std_logic_1164.all;
-- use IEEE.NUMERIC_STD.all;

entity bcd7seg is
	PORT(
        sw_debounce		: IN STD_LOGIC_VECTOR(15 downto 0);
        an				: OUT STD_LOGIC_VECTOR(3 downto 0); -- coluna dos dados (anodo)
        seg				: OUT STD_LOGIC_VECTOR(6 downto 0) -- próprio segmento
    );
end bcd7seg;

entity bcd_decoder is
	PORT(
    	input : IN STD_LOGIC_VECTOR(3 downto 0);
        output: OUT STD_LOGIC_VECTOR(6 downto 0)
    );
end bcd_decoder;

architecture structural of bcd7seg is
	component bcd_decoder is
    	PORT(
        	input : IN STD_LOGIC_VECTOR(3 downto 0);
            output: OUT STD_LOGIC_VECTOR(6 downto 0)
        );
    end component;
    
    signal seg1, seg2, seg3, seg4: STD_LOGIC_VECTOR(6 downto 0);
    signal is_negative: STD_LOGIC;
    begin 
    	decoder1: bcd_decoder port map (input=>sw_debounce(3 downto 0), output=>seg1);
        decoder2: bcd_decoder port map (input=>sw_debounce(7 downto 4), output=>seg2);
        decoder3: bcd_decoder port map (input=>sw_debounce(11 downto 8), output=>seg3);
        decoder4: bcd_decoder port map (input=>sw_debounce(15 downto 12), output=>seg4);
        seg<="0111111" when is_negative='1' else seg4; --padrão de aplicação do '-'
        an <= "0000"; -- digitos mostrados completamente
end architecture;

architecture combinational of bcd_decoder is
begin
	process(input)
    	begin
        	case input is
              WHEN "0000" => output <= "1000000"; --0
              WHEN "0001" => output <= "1111001"; --1
              WHEN "0010" => output <= "0100100"; --2
              WHEN "0011" => output <= "0110000"; --3
              WHEN "0100" => output <= "0011001"; --4
              WHEN "0101" => output <= "0010010"; --5
              WHEN "0110" => output <= "0000010"; --6
              WHEN "0111" => output <= "1111000"; --7
              WHEN "1000" => output <= "0000000"; --8
              WHEN "1001" => output <= "0011000"; --9
              WHEN others => output <= "1000000";
          	end case;
     end process;
end combinational;

somador_sub/soma_sub.vhd
-- by: @jtfrl

-- SOMADOR COMPLETO COM RIPPLE CARRY
library IEEE;
use IEEE.std_logic_1164.all;
use IEEE.NUMERIC_STD.all;

entity soma_sub is
	PORT(
    	A	 	: IN STD_LOGIC_VECTOR(11 DOWNTO 0); -- cada dígito tem 4 bits
        B		: IN STD_LOGIC_VECTOR(11 DOWNTO 0);
		op		: IN STD_LOGIC; -- '0' para '+' e 1 para '-'
        Cout	: OUT STD_LOGIC;
        S		: OUT STD_LOGIC_VECTOR(11 DOWNTO 0); -- resultado de soma ou subtração
    );
end entity;

  
architecture dataflow of soma_sub is 
    -- soma de cada par de dígitos e seu respec. carry
	    signal op_col : STD_LOGIC_VECTOR(11 DOWNTO 0);
	    signal carry	: STD_LOGIC_VECTOR(12 DOWNTO 0); -- carry in
	begin
		-- operações
	    op_col<=(not B) when op='1' else B; -- troca de bits para subtração
	    carry(0)<=op; 
	    
	    gen_bits: for i in 0 to 11 generate
	    	S(i) <= A(i) XOR op_col(i) XOR carry(i)
	        carry(i+1)<= (A(i) AND op_col(i)) OR
	        			 (A(i) AND carry(i))  OR
	                     (op_col(i) AND carry(i));
	    end generate;
	    
	    Cout<=carry(12);
	 
	 end architecture;
	-- op0:
 --    	s0<= A xor B xor Cin;
 --        c0<= (A and Cin) or (B and Cin) or (A and B);
 --    op1: 
 --    	s1<= Cin xor s0 xor Cin;
 --        Cout<= (s0 and Cin) or (s1 and Cin) or (s0 and s1);
 --    op2:
 --   	 	S<= A xor B xor Cin;
 --        Cout<= (A and Cin) or (B and Cin) or (A and B);
 --    carry<=c1 or s2;
    
end dataflow;

somador_sub/kbd_encoder.vhd
-- impl; @jtfl
-- TECLADO 0-9 PARA ENTRADAS A e B (DÍGITOS)
-- Deve receber
-- >>> sinais de ADD + e de SUB -
-- >>> dígitos de zero a 9
-- 
-- Deve retornar
-- <<< Vetores de dígitos (000 a 999)
-- <<< A op de operador (ADD ou SUB) via saída OP

library IEEE;
use IEEE.std_logic_1164.all;
use IEEE.NUMERIC_STD.all;

entity kbd_encoder is
	PORT(
    	clk 	: IN STD_LOGIC;
        rst		: IN STD_LOGIC;
      	row_in	: IN STD_LOGIC_VECTOR(3 DOWNTO 0);  
        col_out	: OUT STD_LOGIC_VECTOR(3 DOWNTO 0);  -- fluxo de input
        dig_A 	: OUT STD_LOGIC_VECTOR(11 DOWNTO 0);
        dig_B 	: OUT STD_LOGIC_VECTOR(11 DOWNTO 0);
		op		: OUT STD_LOGIC
    );
end kbd_encoder;

-- == ESCANEAMENTO E DECODIFICAÇÃO
architecture behavioral of kbd_encoder is 
	SIGNAL scan_col		: INTEGER range 0 to 3:=0;
    SIGNAL key_code 	: STD_LOGIC_VECTOR(3 DOWNTO 0); -- 0-9
    -- >< era key_strobe
    SIGNAL status_idle 	: STD_LOGIC :='0'; --define se está ocupado ou não
    
    -- ajuda a converter os números em binário (BCD)
    FUNCTION bin_to_bcd (bin: integer) return STD_LOGIC_VECTOR is 
    	variable bcd : STD_LOGIC_VECTOR(11 DOWNTO 0):= (others=> '0');
        variable temp: integer;
       begin 
       	if bin>999 then temp:=999;
        else temp:=bin;
        end if;
        for i in 0 to 2 loop
        	bcd(i*4+3 downto i*4) :=STD_LOGIC_VECTOR(to_unsigned((temp/10**i)) mod 10,4);
        end loop;
     return bcd;
     end function;
begin
 --=== LOGICA COMBINACIONAL
 
 col_out<="1110"; -- valor digitado para cada numero
 process(row_in, col_out)
   begin 
   key_code<="1111"; -- sem tecla pressionada
   status_idle<='0';
   case row_in is
   	when "1110"=> -- linha 0 ativa
    	case col_out is
            WHEN "1110" => key_code <= "0001"; status_idle<='1'; -- digitou 1
            WHEN "1101" => key_code <= "0010"; status_idle<='1'; -- digitou 2
            WHEN "1011" => key_code <= "0011"; status_idle<='1'; -- digitou 3
            WHEN "0111" => key_code <= "0100"; status_idle<='1'; -- digitou '+'
            WHEN others => NULL;
        end case;
    when "1101"=> -- linha 1 ativa
    	case col_out is
            WHEN "1110" => key_code <= "0100"; status_idle<='1'; -- digitou 4
            WHEN "1101" => key_code <= "0101"; status_idle<='1'; -- digitou 5
            WHEN "1011" => key_code <= "0110"; status_idle<='1'; -- digitou 6
            WHEN "0111" => key_code <= "1011"; status_idle<='-'; -- digitou '-'
        	WHEN others => NULL;
         end case;
     when "1011"=> -- linha 2 ativa
    	case col_out is
            WHEN "1110" => key_code <= "0111"; status_idle<='1'; -- digitou 7
            WHEN "1101" => key_code <= "1000"; status_idle<='1'; -- digitou 8
            WHEN "1011" => key_code <= "1001"; status_idle<='1'; -- digitou 9
            WHEN others => NULL;
         end case;
      when "0111"=> -- linha 3 ativa
    	case col_out is
       		WHEN "1101" => key_code <= "0000"; status_idle<='1'; -- digitou 0
            WHEN others => NULL;
		end case;
      when others=> null;
     end case;
  end process;
     
     
  process(clk, rst)
	variable num_A 		: INTEGER range 0 to 999 := 0;
    variable num_B 		: INTEGER range 0 to 999 := 0;
    variable atual_dig 	: INTEGER range 0 to 9   := 0; -- inteiro atual que está sendo digitado
    variable state		: INTEGER range 0 to 1	 := 0; -- se o usuário digita a entrada de A ou de B
    variable prev_strobe: STD_LOGIC 			 := '0';
  begin 
  	if rst='1' then
    	num_A:=0;
        num_B:=0;
        state<=0;
        op<='0';
        dig_A<=(others=>'0');
        dig_B<=(others=>'0');
        prev_strobe<='0';
     elsif rising_edge(clk) then
     	if (status_idle='1' and prev_strobe='0') then
        	if (key_code >= "0000" and key_code <= "1001") then
            	atual_dig:=to_integer(unsigned(key_code));
                -- shifts (mudança de potência de dez)
                if state=0 then
                	if num_A<=99 then
                    	num_A:=(num_A * 10) + atual_dig;
                    end if;
                    dig_A<=bin_to_bcd(num_A);
                else
                	if num_B<=99 then
                    	num_B:=(num_B * 10) + atual_dig;
                    end if;
                    dig_B<=bin_to_bcd(num_B);
                end if;

                elsif (key_code="1010" or key_code="1011") then
                	if key_code="1010" then
                    	op<='0'; -- opera '+'
                        -- note que como a variável é declarada como constante, não usamos :=
                    else
                    	op<='1'; -- opera '-'
                    end if;
                    
                    state:=1; -- estado é uma variável (indicamos que houve interação)
                end if;
                prev_strobe:=status_idle;

                end if;  
    end if;
end process;
end Behavioral;

somador_sub/top_calculator.vhd
-- by: @jtfrl 
-- interligação dos três modulos
library IEEE;
use IEEE.STD_LOGIC_1164.ALL;
use IEEE.NUMERIC_STD.ALL;

entity calc is
	PORT(
    	clk				: IN STD_LOGIC;
        rst				: IN STD_LOGIC;
        row_in			: IN STD_LOGIC_VECTOR(3 downto 0);
        col_out			: OUT STD_LOGIC_VECTOR(3 downto 0);
        
        -- 7seg
        an				: OUT STD_LOGIC_VECTOR(3 downto 0);
        seg				: OUT STD_LOGIC_VECTOR(6 downto 0);
        Cout			: OUT STD_LOGIC
        
    );
end entity;

architecture structural of calc is
	signal dig_A		: STD_LOGIC_VECTOR(11 downto 0);
    signal dig_B		: STD_LOGIC_VECTOR(11 downto 0);
    signal op			: STD_LOGIC;
    signal resultado 	: STD_LOGIC_VECTOR(11 downto 0);
    signal overflow		: STD_LOGIC_VECTOR(12 downto 0);

begin 
	
    kb 			: entity work.kbd_encoder
    	port map(
        	clk		=> 	clk,
            rst		=> 	rst,
            row_in	=>	row_in,
            col_out	=>	col_out,
            dig_A	=>	dig_A,
            dig_B	=> 	dig_B,
            op		=> 	op
        );
    adder		: entity work.soma_sub
        port map(
        	A		=> dig_A,
            B		=> dig_B,
            op		=> op,
            Cout	=> overflow(12),
            S		=> resultado
            );

    -- subtractor	: entity work.soma_sub
    --     port map(
    --         A		=> dig_A,
    --         B		=> dig_B,
    --         op		=> '1'
    --         Cout	=> overflow(12),
    --         S		=> resultado
    --         );
    
    bcd7seg		: entity work.bcd7seg
    	port map(
        	sw_debounce =>  resultado & "0000", -- indica estado de desocupação
            an			=> an,
            seg			=> seg
        );
     
    Cout <= overflow(12);
end architecture;

somador_sub/tb_calculator.vhd
library IEEE;
use IEEE.std_logic_1164.all;
use IEEE.numeric_std.all;

entity tb_calculator is
    -- sem entradas aqui
end tb_calculator;

architecture behavior of tb_calculator is
    component calc
        PORT(
            clk     : IN STD_LOGIC;
            rst     : IN STD_LOGIC;    
            row_in  : IN STD_LOGIC_VECTOR(3 downto 0);
            -- DISPLAY
            col_out : OUT STD_LOGIC_VECTOR(3 downto 0);
            an      : OUT STD_LOGIC_VECTOR(3 downto 0);
            seg     : OUT STD_LOGIC_VECTOR(6 downto 0);
            Cout    : OUT STD_LOGIC
        );
    end component;

signal clk      : STD_LOGIC :='0';
signal rst      : STD_LOGIC :='1'; 

signal row_in   : STD_LOGIC_VECTOR(3 downto 0) := "1111";
signal col_out  : STD_LOGIC_VECTOR(3 downto 0);
signal an       : STD_LOGIC_VECTOR(3 downto 0);
signal seg      : STD_LOGIC_VECTOR(6 downto 0);
signal cout_tb  : STD_LOGIC;

constant clk_period: time:=20 ns; -- 50 Mhz

procedure press_key(
    signal row_sig        : OUT STD_LOGIC_VECTOR(3 downto 0);
    signal clk_sig        : IN STD_LOGIC;
    constant row_pattern  : IN STD_LOGIC_VECTOR(3 downto 0);
    constant col_pattern  : IN STD_LOGIC_VECTOR(3 downto 0)
) is

    begin
        row_sig<=row_pattern;

        wait until rising_edge(clk_sig);
        wait until rising_edge(clk_sig);
        wait until rising_edge(clk_sig);

        -- solta a tecla
        row_sig<="1111";

        -- aguarda debounce
        wait until rising_edge(clk_sig);
        wait until rising_edge(clk_sig);


    end procedure;

begin 

        uet: calc PORT MAP(
            clk         =>clk,
            rst         =>rst,
            row_in      =>row_in,
            col_out     =>col_out,
            an          =>an,
            seg         =>seg,
            Cout        =>cout_tb
        );

        clk_process: process
        begin
            clk <= '0';
            wait for clk_period/2;   
            clk <= '1';                
            wait for clk_period/2;
        end process;
        
        -- estimulador de processo
        stim_proc: process
        begin
            wait for 100 ns;
            rst <= '1';
            wait for 100 ns;   
            rst <= '0';                
            wait for 50 ns;

        report "COMECANDO TESTE 1: 7+3";

        -- 1 para executar
        press_key(row_in, clk, "1110", "1110");
        -- 7 pressionado
        press_key(row_in, clk, "1011", "1110");
        -- soma
        press_key(row_in, clk, "1110", "0111");
        -- 3 pressionado
        press_key(row_in, clk, "1110", "1011");
        -- 0 (checar)
        press_key(row_in, clk, "0111", "1101");

        wait for 200 ns;
        report "TESTE 1 FINALIZADO. CHEQUE AS ONDAS NO GTK";

        report "COMECANDO TESTE 2: 9-2";
        -- 9 pressionado
        press_key(row_in, clk, "1011", "1011");
        -- subtração
        press_key(row_in, clk, "0111", "1101");
        
        press_key(row_in, clk, "1101", "0111");
        -- 2 pressionado
        press_key(row_in, clk, "1110", "1101");
        
        press_key(row_in, clk, "0111", "1101");

        wait for 200 ns;
        report "TESTE 2 FINALIZADO. CHEQUE AS ONDAS NO GTK";
        
        report "COMECANDO TESTE 3: 5+5";
        press_key(row_in, clk, "1101", "1101");
        press_key(row_in, clk, "0111", "1101");
        press_key(row_in, clk, "1110", "0111");
        press_key(row_in, clk, "1101", "1101");
        press_key(row_in, clk, "0111", "1101");

        wait for 200 ns;
        report "TESTE 3 FINALIZADO. CHEQUE AS ONDAS NO GTK";

        report "COMECANDO TESTE 4: 8-8";
        press_key(row_in, clk, "1011", "1101");
        press_key(row_in, clk, "0111", "1101");
        press_key(row_in, clk, "1101", "0111");
        press_key(row_in, clk, "1011", "1101");
        press_key(row_in, clk, "0111", "1101");

        wait for 200 ns;

        report "TESTE 4 FINALIZADO. CHEQUE AS ONDAS NO GTK";

        wait for 100 ns;
        report "TODOS OS TESTES FORAM EXECUTADOS COM SUCESSO";
        wait;
    end process;
end behavior;

somador_sub/waves_calc.vcd
$date
  Sun Sep 27 23:27:23 2026
$end
$version
  GHDL v0
$end
$timescale
  1 fs
$end
$scope module standard $end
$upscope $end
$scope module textio $end
$upscope $end
$scope module std_logic_1164 $end
$upscope $end
$scope module numeric_std $end
$upscope $end
$scope module tb_calculator $end
$var reg 1 ! clk $end
$var reg 1 " rst $end
$var reg 4 # row_in[3:0] $end
$var reg 4 $ col_out[3:0] $end
$var reg 4 % an[3:0] $end
$var reg 7 & seg[6:0] $end
$var reg 1 ' cout_tb $end
$scope module uet $end
$var reg 1 ( clk $end
$var reg 1 ) rst $end
$var reg 4 * row_in[3:0] $end
$var reg 4 + col_out[3:0] $end
$var reg 4 , an[3:0] $end
$var reg 7 - seg[6:0] $end
$var reg 1 . cout $end
$var reg 12 / dig_a[11:0] $end
$var reg 12 0 dig_b[11:0] $end
$var reg 1 1 op $end
$var reg 12 2 resultado[11:0] $end
$var reg 13 3 overflow[12:0] $end
$scope module kb $end
$var reg 1 4 clk $end
$var reg 1 5 rst $end
$var reg 4 6 row_in[3:0] $end
$var reg 4 7 col_out[3:0] $end
$var reg 12 8 dig_a[11:0] $end
$var reg 12 9 dig_b[11:0] $end
$var reg 1 : op $end
$var integer 32 ; scan_col $end
$var reg 4 < key_code[3:0] $end
$var reg 1 = status_idle $end
$upscope $end
$scope module adder $end
$var reg 12 > a[11:0] $end
$var reg 12 ? b[11:0] $end
$var reg 1 @ op $end
$var reg 1 A cout $end
$var reg 12 B s[11:0] $end
$var reg 12 C op_col[11:0] $end
$var reg 13 D carry[12:0] $end
$scope module gen_bits(0) $end
$upscope $end
$scope module gen_bits(1) $end
$upscope $end
$scope module gen_bits(2) $end
$upscope $end
$scope module gen_bits(3) $end
$upscope $end
$scope module gen_bits(4) $end
$upscope $end
$scope module gen_bits(5) $end
$upscope $end
$scope module gen_bits(6) $end
$upscope $end
$scope module gen_bits(7) $end
$upscope $end
$scope module gen_bits(8) $end
$upscope $end
$scope module gen_bits(9) $end
$upscope $end
$scope module gen_bits(10) $end
$upscope $end
$scope module gen_bits(11) $end
$upscope $end
$upscope $end
$scope module bcd7seg $end
$var reg 16 E sw_debounce[15:0] $end
$var reg 4 F an[3:0] $end
$var reg 7 G seg[6:0] $end
$var reg 7 H seg1[6:0] $end
$var reg 7 I seg2[6:0] $end
$var reg 7 J seg3[6:0] $end
$var reg 7 K seg4[6:0] $end
$var reg 1 L is_negative $end
$scope module decoder1 $end
$var reg 4 M input[3:0] $end
$var reg 7 N output[6:0] $end
$upscope $end
$scope module decoder2 $end
$var reg 4 O input[3:0] $end
$var reg 7 P output[6:0] $end
$upscope $end
$scope module decoder3 $end
$var reg 4 Q input[3:0] $end
$var reg 7 R output[6:0] $end
$upscope $end
$scope module decoder4 $end
$var reg 4 S input[3:0] $end
$var reg 7 T output[6:0] $end
$upscope $end
$upscope $end
$upscope $end
$upscope $end
$enddefinitions $end
#0
0!
1"
b1111 #
b1110 $
b0000 %
b1000000 &
0'
0(
1)
b1111 *
b1110 +
b0000 ,
b1000000 -
0.
b000000000000 /
b000000000000 0
01
b000000000000 2
b0UUUUUUUUUUUU 3
04
15
b1111 6
b1110 7
b000000000000 8
b000000000000 9
0:
b0 ;
b1111 <
0=
b000000000000 >
b000000000000 ?
0@
0A
b000000000000 B
b000000000000 C
b0000000000000 D
b0000000000000000 E
b0000 F
b1000000 G
b1000000 H
b1000000 I
b1000000 J
b1000000 K
UL
b0000 M
b1000000 N
b0000 O
b1000000 P
b0000 Q
b1000000 R
b0000 S
b1000000 T
#10000000
1!
1(
14
#20000000
0!
0(
04
#30000000
1!
1(
14
#40000000
0!
0(
04
#50000000
1!
1(
14
#60000000
0!
0(
04
#70000000
1!
1(
14
#80000000
0!
0(
04
#90000000
1!
1(
14
#100000000
0!
0(
04
#110000000
1!
1(
14
#120000000
0!
0(
04
#130000000
1!
1(
14
#140000000
0!
0(
04
#150000000
1!
1(
14
#160000000
0!
0(
04
#170000000
1!
1(
14
#180000000
0!
0(
04
#190000000
1!
1(
14
#200000000
0!
0"
0(
0)
04
05
#210000000
1!
1(
14
#220000000
0!
0(
04
#230000000
1!
1(
14
#240000000
0!
0(
04
#250000000
1!
b1110 #
1(
b1110 *
14
b1110 6
b0001 <
1=
#260000000
0!
0(
04
#270000000
1!
1(
b000000000001 /
b000000000001 2
14
b000000000001 8
b000000000001 >
b000000000001 B
b0000000000010000 E
b1111001 I
b0001 O
b1111001 P
#280000000
0!
0(
04
#290000000
1!
b1111 #
1(
b1111 *
14
b1111 6
b1111 <
0=
#300000000
0!
0(
04
#310000000
1!
1(
14
#320000000
0!
0(
04
#330000000
1!
b1011 #
1(
b1011 *
14
b1011 6
b0111 <
1=
#340000000
0!
0(
04
#350000000
1!
1(
14
#360000000
0!
0(
04
#370000000
1!
1(
14
#380000000
0!
0(
04
#390000000
1!
b1111 #
1(
b1111 *
14
b1111 6
b1111 <
0=
#400000000
0!
0(
04
#410000000
1!
1(
14
#420000000
0!
0(
04
#430000000
1!
b1110 #
1(
b1110 *
14
b1110 6
b0001 <
1=
#440000000
0!
0(
04
#450000000
1!
1(
14
#460000000
0!
0(
04
#470000000
1!
1(
14
#480000000
0!
0(
04
#490000000
1!
b1111 #
1(
b1111 *
14
b1111 6
b1111 <
0=
#500000000
0!
0(
04
#510000000
1!
1(
14
#520000000
0!
0(
04
#530000000
1!
b1110 #
1(
b1110 *
14
b1110 6
b0001 <
1=
#540000000
0!
0(
04
#550000000
1!
1(
14
#560000000
0!
0(
04
#570000000
1!
1(
14
#580000000
0!
0(
04
#590000000
1!
b1111 #
1(
b1111 *
14
b1111 6
b1111 <
0=
#600000000
0!
0(
04
#610000000
1!
1(
14
#620000000
0!
0(
04
#630000000
1!
b0111 #
1(
b0111 *
14
b0111 6
#640000000
0!
0(
04
#650000000
1!
1(
14
#660000000
0!
0(
04
#670000000
1!
1(
14
#680000000
0!
0(
04
#690000000
1!
b1111 #
1(
b1111 *
14
b1111 6
#700000000
0!
0(
04
#710000000
1!
1(
14
#720000000
0!
0(
04
#730000000
1!
1(
14
#740000000
0!
0(
04
#750000000
1!
1(
14
#760000000
0!
0(
04
#770000000
1!
1(
14
#780000000
0!
0(
04
#790000000
1!
1(
14
#800000000
0!
0(
04
#810000000
1!
1(
14
#820000000
0!
0(
04
#830000000
1!
1(
14
#840000000
0!
0(
04
#850000000
1!
1(
14
#860000000
0!
0(
04
#870000000
1!
1(
14
#880000000
0!
0(
04
#890000000
1!
1(
14
#900000000
0!
0(
04
#910000000
1!
1(
14
#920000000
0!
0(
04
#930000000
1!
b1011 #
1(
b1011 *
14
b1011 6
b0111 <
1=
#940000000
0!
0(
04
#950000000
1!
1(
14
#960000000
0!
0(
04
#970000000
1!
b1111 #
1(
b1111 *
14
b1111 6
b1111 <
0=
#980000000
0!
0(
04
#990000000
1!
1(
14
#1000000000
0!
0(
04
#1010000000
1!
b0111 #
1(
b0111 *
14
b0111 6
#1020000000
0!
0(
04
#1030000000
1!
1(
14
#1040000000
0!
0(
04
#1050000000
1!
1(
14
#1060000000
0!
0(
04
#1070000000
1!
b1111 #
1(
b1111 *
14
b1111 6
#1080000000
0!
0(
04
#1090000000
1!
1(
14
#1100000000
0!
0(
04
#1110000000
1!
b1101 #
1(
b1101 *
14
b1101 6
b0100 <
1=
#1120000000
0!
0(
04
#1130000000
1!
1(
14
#1140000000
0!
0(
04
#1150000000
1!
1(
14
#1160000000
0!
0(
04
#1170000000
1!
b1111 #
1(
b1111 *
14
b1111 6
b1111 <
0=
#1180000000
0!
0(
04
#1190000000
1!
1(
14
#1200000000
0!
0(
04
#1210000000
1!
b1110 #
1(
b1110 *
14
b1110 6
b0001 <
1=
#1220000000
0!
0(
04
#1230000000
1!
1(
14
#1240000000
0!
0(
04
#1250000000
1!
1(
14
#1260000000
0!
0(
04
#1270000000
1!
b1111 #
1(
b1111 *
14
b1111 6
b1111 <
0=
#1280000000
0!
0(
04
#1290000000
1!
1(
14
#1300000000
0!
0(
04
#1310000000
1!
b0111 #
1(
b0111 *
14
b0111 6
#1320000000
0!
0(
04
#1330000000
1!
1(
14
#1340000000
0!
0(
04
#1350000000
1!
1(
14
#1360000000
0!
0(
04
#1370000000
1!
b1111 #
1(
b1111 *
14
b1111 6
#1380000000
0!
0(
04
#1390000000
1!
1(
14
#1400000000
0!
0(
04
#1410000000
1!
1(
14
#1420000000
0!
0(
04
#1430000000
1!
1(
14
#1440000000
0!
0(
04
#1450000000
1!
1(
14
#1460000000
0!
0(
04
#1470000000
1!
1(
14
#1480000000
0!
0(
04
#1490000000
1!
1(
14
#1500000000
0!
0(
04
#1510000000
1!
1(
14
#1520000000
0!
0(
04
#1530000000
1!
1(
14
#1540000000
0!
0(
04
#1550000000
1!
1(
14
#1560000000
0!
0(
04
#1570000000
1!
1(
14
#1580000000
0!
0(
04
#1590000000
1!
1(
14
#1600000000
0!
0(
04
#1610000000
1!
b1101 #
1(
b1101 *
14
b1101 6
b0100 <
1=
#1620000000
0!
0(
04
#1630000000
1!
1(
14
#1640000000
0!
0(
04
#1650000000
1!
b1111 #
1(
b1111 *
14
b1111 6
b1111 <
0=
#1660000000
0!
0(
04
#1670000000
1!
1(
14
#1680000000
0!
0(
04
#1690000000
1!
b0111 #
1(
b0111 *
14
b0111 6
#1700000000
0!
0(
04
#1710000000
1!
1(
14
#1720000000
0!
0(
04
#1730000000
1!
1(
14
#1740000000
0!
0(
04
#1750000000
1!
b1111 #
1(
b1111 *
14
b1111 6
#1760000000
0!
0(
04
#1770000000
1!
1(
14
#1780000000
0!
0(
04
#1790000000
1!
b1110 #
1(
b1110 *
14
b1110 6
b0001 <
1=
#1800000000
0!
0(
04
#1810000000
1!
1(
14
#1820000000
0!
0(
04
#1830000000
1!
1(
14
#1840000000
0!
0(
04
#1850000000
1!
b1111 #
1(
b1111 *
14
b1111 6
b1111 <
0=
#1860000000
0!
0(
04
#1870000000
1!
1(
14
#1880000000
0!
0(
04
#1890000000
1!
b1101 #
1(
b1101 *
14
b1101 6
b0100 <
1=
#1900000000
0!
0(
04
#1910000000
1!
1(
14
#1920000000
0!
0(
04
#1930000000
1!
1(
14
#1940000000
0!
0(
04
#1950000000
1!
b1111 #
1(
b1111 *
14
b1111 6
b1111 <
0=
#1960000000
0!
0(
04
#1970000000
1!
1(
14
#1980000000
0!
0(
04
#1990000000
1!
b0111 #
1(
b0111 *
14
b0111 6
#2000000000
0!
0(
04
#2010000000
1!
1(
14
#2020000000
0!
0(
04
#2030000000
1!
1(
14
#2040000000
0!
0(
04
#2050000000
1!
b1111 #
1(
b1111 *
14
b1111 6
#2060000000
0!
0(
04
#2070000000
1!
1(
14
#2080000000
0!
0(
04
#2090000000
1!
1(
14
#2100000000
0!
0(
04
#2110000000
1!
1(
14
#2120000000
0!
0(
04
#2130000000
1!
1(
14
#2140000000
0!
0(
04
#2150000000
1!
1(
14
#2160000000
0!
0(
04
#2170000000
1!
1(
14
#2180000000
0!
0(
04
#2190000000
1!
1(
14
#2200000000
0!
0(
04
#2210000000
1!
1(
14
#2220000000
0!
0(
04
#2230000000
1!
1(
14
#2240000000
0!
0(
04
#2250000000
1!
1(
14
#2260000000
0!
0(
04
#2270000000
1!
1(
14
#2280000000
0!
0(
04
#2290000000
1!
b1011 #
1(
b1011 *
14
b1011 6
b0111 <
1=
#2300000000
0!
0(
04
#2310000000
1!
1(
14
#2320000000
0!
0(
04
#2330000000
1!
b1111 #
1(
b1111 *
14
b1111 6
b1111 <
0=
#2340000000
0!
0(
04
#2350000000
1!
1(
14
#2360000000
0!
0(
04
#2370000000
1!
b0111 #
1(
b0111 *
14
b0111 6
#2380000000
0!
0(
04
#2390000000
1!
1(
14
#2400000000
0!
0(
04
#2410000000
1!
1(
14
#2420000000
0!
0(
04
#2430000000
1!
b1111 #
1(
b1111 *
14
b1111 6
#2440000000
0!
0(
04
#2450000000
1!
1(
14
#2460000000
0!
0(
04
#2470000000
1!
b1101 #
1(
b1101 *
14
b1101 6
b0100 <
1=
#2480000000
0!
0(
04
#2490000000
1!
1(
14
#2500000000
0!
0(
04
#2510000000
1!
1(
14
#2520000000
0!
0(
04
#2530000000
1!
b1111 #
1(
b1111 *
14
b1111 6
b1111 <
0=
#2540000000
0!
0(
04
#2550000000
1!
1(
14
#2560000000
0!
0(
04
#2570000000
1!
b1011 #
1(
b1011 *
14
b1011 6
b0111 <
1=
#2580000000
0!
0(
04
#2590000000
1!
1(
14
#2600000000
0!
0(
04
#2610000000
1!
1(
14
#2620000000
0!
0(
04
#2630000000
1!
b1111 #
1(
b1111 *
14
b1111 6
b1111 <
0=
#2640000000
0!
0(
04
#2650000000
1!
1(
14
#2660000000
0!
0(
04
#2670000000
1!
b0111 #
1(
b0111 *
14
b0111 6
#2680000000
0!
0(
04
#2690000000
1!
1(
14
#2700000000
0!
0(
04
#2710000000
1!
1(
14
#2720000000
0!
0(
04
#2730000000
1!
b1111 #
1(
b1111 *
14
b1111 6
